Algorithm_Rayleigh/__init__.py
Algorithm_Rayleigh/algorithmRayleigh.cp310-win_amd64.pyd
Algorithm_Rayleigh/dataPreProcessing.cp310-win_amd64.pyd
Algorithm_Rayleigh/main.cp310-win_amd64.pyd
Algorithm_Rayleigh-0.1.1.dist-info/METADATA
Algorithm_Rayleigh-0.1.1.dist-info/WHEEL
Algorithm_Rayleigh-0.1.1.dist-info/top_level.txt
Algorithm_Rayleigh-0.1.1.dist-info/RECORD
